{
  "info": {
    "description": "data",
    "version": "1.0",
    "year": 2025,
    "contributor": "search engine",
    "source": "no_augmentation",
    "license": {
      "name": "Creative Commons Attribution 4.0 International",
      "url": "https://creativecommons.org/licenses/by/4.0/"
    },
    "leaf_info": {
      "leaf_number": 133.0,
      "source": "plant_village_classification",
      "original_filename": "JR_HL 8594.JPG"
    }
  },
  "images": [
    {
      "id": 6631360860,
      "width": 256,
      "height": 256,
      "file_name": "image (1082).JPG",
      "size": 16366,
      "format": "JPG",
      "url": "",
      "hash": "",
      "status": "success",
      "original_filename": "JR_HL 8594.JPG",
      "pvc_filename": "bdba3ee1-95a1-45b8-9c31-21add45a86aa___JR_HL 8594.JPG"
    }
  ],
  "annotations": [
    {
      "id": 4924582870,
      "image_id": 6631360860,
      "category_id": 2000000019,
      "segmentation": [],
      "area": 1217,
      "bbox": [
        148,
        79,
        108,
        177
      ]
    },
    {
      "id": 7152696870,
      "image_id": 6631360860,
      "category_id": 2000000019,
      "segmentation": [],
      "area": 273,
      "bbox": [
        13,
        80,
        32,
        54
      ]
    }
  ],
  "categories": [
    {
      "id": 2000000019,
      "name": "healthy",
      "supercategory": "Pepper,_bell"
    }
  ]
}