{
  "info": {
    "description": "data",
    "version": "1.0",
    "year": 2025,
    "contributor": "search engine",
    "source": "no_augmentation",
    "license": {
      "name": "Creative Commons Attribution 4.0 International",
      "url": "https://creativecommons.org/licenses/by/4.0/"
    },
    "leaf_info": {
      "leaf_number": 51.0,
      "source": "plant_village_classification",
      "original_filename": "JR_HL 7750.JPG"
    }
  },
  "images": [
    {
      "id": 5572750327,
      "width": 256,
      "height": 256,
      "file_name": "image (1430).JPG",
      "size": 13668,
      "format": "JPG",
      "url": "",
      "hash": "",
      "status": "success",
      "original_filename": "JR_HL 7750.JPG",
      "pvc_filename": "f102520d-aa05-452f-9c24-6e480d59112e___JR_HL 7750.JPG"
    }
  ],
  "annotations": [
    {
      "id": 7350115337,
      "image_id": 5572750327,
      "category_id": 2000000019,
      "segmentation": [],
      "area": 103,
      "bbox": [
        66,
        226,
        16,
        18
      ]
    },
    {
      "id": 1026108337,
      "image_id": 5572750327,
      "category_id": 2000000019,
      "segmentation": [],
      "area": 209,
      "bbox": [
        57,
        196,
        24,
        33
      ]
    },
    {
      "id": 2976593337,
      "image_id": 5572750327,
      "category_id": 2000000019,
      "segmentation": [],
      "area": 263,
      "bbox": [
        37,
        157,
        22,
        32
      ]
    },
    {
      "id": 6996840337,
      "image_id": 5572750327,
      "category_id": 2000000019,
      "segmentation": [],
      "area": 121,
      "bbox": [
        163,
        153,
        13,
        27
      ]
    },
    {
      "id": 1856776337,
      "image_id": 5572750327,
      "category_id": 2000000019,
      "segmentation": [],
      "area": 874,
      "bbox": [
        213,
        47,
        41,
        127
      ]
    },
    {
      "id": 6317475337,
      "image_id": 5572750327,
      "category_id": 2000000019,
      "segmentation": [],
      "area": 527,
      "bbox": [
        75,
        13,
        30,
        45
      ]
    }
  ],
  "categories": [
    {
      "id": 2000000019,
      "name": "healthy",
      "supercategory": "Pepper,_bell"
    }
  ]
}