{
  "info": {
    "description": "data",
    "version": "1.0",
    "year": 2025,
    "contributor": "search engine",
    "source": "no_augmentation",
    "license": {
      "name": "Creative Commons Attribution 4.0 International",
      "url": "https://creativecommons.org/licenses/by/4.0/"
    },
    "leaf_info": {
      "leaf_number": 93.0,
      "source": "plant_village_classification",
      "original_filename": "JR_HL 8205.JPG"
    }
  },
  "images": [
    {
      "id": 9577025083,
      "width": 256,
      "height": 256,
      "file_name": "image (1255).JPG",
      "size": 15024,
      "format": "JPG",
      "url": "",
      "hash": "",
      "status": "success",
      "original_filename": "JR_HL 8205.JPG",
      "pvc_filename": "da6be4a5-51ff-4bea-894e-9c5d1d3f699d___JR_HL 8205.JPG"
    }
  ],
  "annotations": [
    {
      "id": 5064490093,
      "image_id": 9577025083,
      "category_id": 2000000019,
      "segmentation": [],
      "area": 306,
      "bbox": [
        98,
        228,
        21,
        28
      ]
    },
    {
      "id": 8004871093,
      "image_id": 9577025083,
      "category_id": 2000000019,
      "segmentation": [],
      "area": 250,
      "bbox": [
        134,
        219,
        28,
        22
      ]
    },
    {
      "id": 2358426093,
      "image_id": 9577025083,
      "category_id": 2000000019,
      "segmentation": [],
      "area": 737,
      "bbox": [
        32,
        147,
        57,
        85
      ]
    },
    {
      "id": 2114559093,
      "image_id": 9577025083,
      "category_id": 2000000019,
      "segmentation": [],
      "area": 1436,
      "bbox": [
        193,
        85,
        43,
        77
      ]
    },
    {
      "id": 2696842093,
      "image_id": 9577025083,
      "category_id": 2000000019,
      "segmentation": [],
      "area": 2871,
      "bbox": [
        79,
        0,
        42,
        147
      ]
    },
    {
      "id": 6555787093,
      "image_id": 9577025083,
      "category_id": 2000000019,
      "segmentation": [],
      "area": 893,
      "bbox": [
        16,
        71,
        24,
        75
      ]
    },
    {
      "id": 6928706093,
      "image_id": 9577025083,
      "category_id": 2000000019,
      "segmentation": [],
      "area": 115,
      "bbox": [
        202,
        41,
        22,
        16
      ]
    }
  ],
  "categories": [
    {
      "id": 2000000019,
      "name": "healthy",
      "supercategory": "Pepper,_bell"
    }
  ]
}