{
  "info": {
    "description": "data",
    "version": "1.0",
    "year": 2025,
    "contributor": "search engine",
    "source": "augmented",
    "license": {
      "name": "Creative Commons Attribution 4.0 International",
      "url": "https://creativecommons.org/licenses/by/4.0/"
    }
  },
  "images": [
    {
      "id": 8029213897,
      "width": 256,
      "height": 256,
      "file_name": "image (1377).JPG",
      "size": 16538,
      "format": "JPG",
      "url": "",
      "hash": "",
      "status": "success"
    }
  ],
  "annotations": [
    {
      "id": 7343212899,
      "image_id": 8029213897,
      "category_id": 1000000019,
      "segmentation": [],
      "area": 6063,
      "bbox": [
        179,
        13,
        54,
        234
      ]
    },
    {
      "id": 5777921899,
      "image_id": 8029213897,
      "category_id": 1000000019,
      "segmentation": [],
      "area": 2719,
      "bbox": [
        26,
        89,
        128,
        128
      ]
    },
    {
      "id": 4615148899,
      "image_id": 8029213897,
      "category_id": 1000000019,
      "segmentation": [],
      "area": 325,
      "bbox": [
        34,
        52,
        26,
        30
      ]
    },
    {
      "id": 8704958899,
      "image_id": 8029213897,
      "category_id": 1000000019,
      "segmentation": [],
      "area": 965,
      "bbox": [
        63,
        0,
        60,
        61
      ]
    }
  ],
  "categories": [
    {
      "id": 1000000019,
      "name": "healthy",
      "supercategory": "Pepper,_bell"
    }
  ]
}