{
  "info": {
    "description": "data",
    "version": "1.0",
    "year": 2025,
    "contributor": "search engine",
    "source": "augmented",
    "license": {
      "name": "Creative Commons Attribution 4.0 International",
      "url": "https://creativecommons.org/licenses/by/4.0/"
    }
  },
  "images": [
    {
      "id": 2289613823,
      "width": 256,
      "height": 256,
      "file_name": "image (225).JPG",
      "size": 15689,
      "format": "JPG",
      "url": "",
      "hash": "",
      "status": "success"
    }
  ],
  "annotations": [
    {
      "id": 8245953825,
      "image_id": 2289613823,
      "category_id": 1000000019,
      "segmentation": [],
      "area": 164,
      "bbox": [
        120,
        200,
        35,
        51
      ]
    },
    {
      "id": 5579957825,
      "image_id": 2289613823,
      "category_id": 1000000019,
      "segmentation": [],
      "area": 1146,
      "bbox": [
        184,
        32,
        65,
        149
      ]
    },
    {
      "id": 4879444825,
      "image_id": 2289613823,
      "category_id": 1000000019,
      "segmentation": [],
      "area": 242,
      "bbox": [
        128,
        0,
        29,
        17
      ]
    }
  ],
  "categories": [
    {
      "id": 1000000019,
      "name": "healthy",
      "supercategory": "Pepper,_bell"
    }
  ]
}